hugophotoswipe/__init__.py
hugophotoswipe/__main__.py
hugophotoswipe/__version__.py
hugophotoswipe/album.py
hugophotoswipe/config.py
hugophotoswipe/hugophotoswipe.py
hugophotoswipe/photo.py
hugophotoswipe/ui.py
hugophotoswipe/utils.py
hugophotoswipe-0.3.1.dist-info/LICENSE
hugophotoswipe-0.3.1.dist-info/METADATA
hugophotoswipe-0.3.1.dist-info/WHEEL
hugophotoswipe-0.3.1.dist-info/entry_points.txt
hugophotoswipe-0.3.1.dist-info/top_level.txt
hugophotoswipe-0.3.1.dist-info/RECORD
