Metadata-Version: 2.1
Name: hugophotoswipe
Version: 0.3.1
Summary: Tool for creating and managing PhotoSwipe albums in Hugo
Home-page: https://github.com/GjjvdBurg/hugophotoswipe
Author: Gertjan van den Burg
Author-email: gertjanvandenburg@gmail.com
License: GPLv3
Classifier: License :: OSI Approved :: GNU General Public License v3 (GPLv3)
Classifier: Programming Language :: Python
Classifier: Programming Language :: Python :: 3
Classifier: Programming Language :: Python :: 3.3
Classifier: Programming Language :: Python :: 3.4
Classifier: Programming Language :: Python :: 3.5
Classifier: Programming Language :: Python :: 3.6
Classifier: Programming Language :: Python :: 3.7
Classifier: Programming Language :: Python :: 3.8
Classifier: Programming Language :: Python :: Implementation :: CPython
Classifier: Programming Language :: Python :: Implementation :: PyPy
Classifier: Intended Audience :: Developers
Requires-Python: >=3.3.0
License-File: LICENSE
Requires-Dist: six
Requires-Dist: tzlocal
Requires-Dist: pytz
Requires-Dist: pyyaml
Requires-Dist: tqdm
Requires-Dist: smartcrop
Provides-Extra: dev
Requires-Dist: green ; extra == 'dev'
Provides-Extra: docs
Provides-Extra: tests
